fruit/__init__.py
fruit/config.py
fruit/fruit.py
fruit/globals.py
fruit/api/__init__.py
fruit/api/api.py
fruit/api/decorators.py
fruit/api/shell.py
fruit/extensions/__init__.py
fruit/extensions/global_providers.py
fruit/modules/__init__.py
fruit/modules/config.py
fruit/modules/console.py
fruit/modules/event.py
fruit/modules/finder.py
fruit/modules/fruitloader.py
fruit/modules/garden.py
fruit/modules/job.py
fruit/modules/patterns.py
fruit/modules/pickup.py
fruit/modules/printing.py
fruit/modules/provider.py
fruit/modules/step.py
fruit/modules/target.py
fruit-0.3.5.dist-info/LICENSE
fruit-0.3.5.dist-info/METADATA
fruit-0.3.5.dist-info/WHEEL
fruit-0.3.5.dist-info/entry_points.txt
fruit-0.3.5.dist-info/top_level.txt
fruit-0.3.5.dist-info/RECORD
